[
    {
      "maidId": "maid-1",
      "availabilities": [
        {
          "day": "2024-09-10",
          "hours": ["09:00", "13:00", "16:00"]
        },
        {
          "day": "2024-09-11",
          "hours": ["10:00", "14:00"]
        }
      ]
    },
    {
      "maidId": "maid-2",
      "availabilities": [
        {
          "day": "2024-09-10",
          "hours": ["08:00", "12:00"]
        },
        {
          "day": "2024-09-12",
          "hours": ["09:00", "11:00", "17:00"]
        }
      ]
    }
  ]
  